LICENSE
MANIFEST.in
README.md
requirements.txt
setup.py
anadroid/Anadroid.py
anadroid/Config.py
anadroid/Types.py
anadroid/__init__.py
anadroid/_version.py
anadroid/ecoanadroid.py
anadroid/main.py
anadroid.egg-info/PKG-INFO
anadroid.egg-info/SOURCES.txt
anadroid.egg-info/dependency_links.txt
anadroid.egg-info/requires.txt
anadroid.egg-info/top_level.txt
anadroid/analysis/AbstractAnalyzer.py
anadroid/analysis/ComposedAnalyzer.py
anadroid/analysis/ExecutionResultsAnalyzer.py
anadroid/analysis/StaticAnalyzer.py
anadroid/analysis/__init__.py
anadroid/analysis/filters/Filter.py
anadroid/analysis/filters/Filters.py
anadroid/analysis/filters/__init__.py
anadroid/analysis/metrics/Issues.py
anadroid/analysis/metrics/Metrics.py
anadroid/analysis/metrics/__init__.py
anadroid/analysis/post_build_analysis/ApkAPIAnalyzer.py
anadroid/analysis/post_build_analysis/EcoAndroidResourceLeaksAnalyzer.py
anadroid/analysis/post_build_analysis/__init__.py
anadroid/analysis/post_execution_analysis/LogAnalyzer.py
anadroid/analysis/post_execution_analysis/ManafaAnalyzer.py
anadroid/analysis/post_execution_analysis/ManafaMethodCoverageAnalyzer.py
anadroid/analysis/post_execution_analysis/OldAnaDroidAnalyzer.py
anadroid/analysis/post_execution_analysis/__init__.py
anadroid/analysis/pre_build_analysis/ADoctorAnalysis.py
anadroid/analysis/pre_build_analysis/ChimeraAnalysis.py
anadroid/analysis/pre_build_analysis/DAAPAnalysis.py
anadroid/analysis/pre_build_analysis/EcoAndroidAnalysis.py
anadroid/analysis/pre_build_analysis/LintAnalysis.py
anadroid/analysis/pre_build_analysis/PMDAnalysis.py
anadroid/analysis/pre_build_analysis/SCCAnalyzer.py
anadroid/analysis/pre_build_analysis/XALintAnalysis.py
anadroid/analysis/pre_build_analysis/__init__.py
anadroid/analysis/results_analysis/__init__.py
anadroid/application/AbstractApplication.py
anadroid/application/AndroidProject.py
anadroid/application/Application.py
anadroid/application/Dependency.py
anadroid/application/ProjectModule.py
anadroid/application/__init__.py
anadroid/build/AbstractBuilder.py
anadroid/build/DummyBuilder.py
anadroid/build/GracleBuildErrorSolver.py
anadroid/build/GradleBuilder.py
