Metadata-Version: 2.2
Name: anadroid
Version: 0.5.61
Summary: PyAnaDroid: A replicable, fully-customizable execution pipeline foranalyzing and benchmarking Android Applications
Home-page: https://github.com/greensoftwarelab/PyAnaDroid
Author: Rui Rua
Author-email: rui.rrua@gmail.com
License: MIT
Project-URL: Bug Tracker, https://github.com/greensoftwarelab/PyAnaDroid/issues
Classifier: License :: OSI Approved :: MIT License
Classifier: Intended Audience :: Science/Research
Classifier: Operating System :: POSIX
Classifier: Programming Language :: Python :: 3.8
Requires-Python: >=3.8
License-File: LICENSE
Requires-Dist: androguard>=3.4.0a1
Requires-Dist: incremental>=17.5.0
Requires-Dist: lxml>=4.6.5
Requires-Dist: six>=1.15.0
Requires-Dist: manafa>=0.3.127
Requires-Dist: physalia==0.0.1.dev122
Requires-Dist: termcolor==1.1.0
Requires-Dist: pylogcatparser>=0.2.7
Requires-Dist: androidviewclient==22.5.1
Dynamic: author
Dynamic: author-email
Dynamic: classifier
Dynamic: description
Dynamic: description-content-type
Dynamic: home-page
Dynamic: license
Dynamic: project-url
Dynamic: requires-dist
Dynamic: requires-python
Dynamic: summary
